sherlog/__init__.py
sherlog/cli.py
sherlog/config.py
sherlog/logger.py
sherlog/monitor.py
sherlog/postgresql.py
sherlog/version.py
sherlog/worker.py
sherlog-0.1.8.dist-info/DESCRIPTION.rst
sherlog-0.1.8.dist-info/METADATA
sherlog-0.1.8.dist-info/RECORD
sherlog-0.1.8.dist-info/WHEEL
sherlog-0.1.8.dist-info/entry_points.txt
sherlog-0.1.8.dist-info/metadata.json
sherlog-0.1.8.dist-info/top_level.txt
