Metadata-Version: 2.0
Name: sherlog
Version: 0.1.8
Summary: Sherlog is an easy to use plug-and-play tool for logs aggregation.
Home-page: https://github.com/sancau/sherlog/
Author: Alexander Tatchin
Author-email: alexander.tatchin@gmail.com
License: MIT
Platform: any
Classifier: Development Status :: 3 - Alpha
Classifier: Intended Audience :: Developers
Classifier: Intended Audience :: End Users/Desktop
Classifier: Intended Audience :: Information Technology
Classifier: Intended Audience :: Science/Research
Classifier: Intended Audience :: System Administrators
Classifier: License :: OSI Approved :: MIT License
Classifier: Operating System :: POSIX
Classifier: Operating System :: MacOS
Classifier: Operating System :: Unix
Classifier: Programming Language :: Python
Classifier: Programming Language :: Python :: 3
Classifier: Topic :: Software Development :: Libraries :: Python Modules
Classifier: Topic :: Internet
Classifier: Topic :: Internet :: Log Analysis
Classifier: Topic :: Scientific/Engineering
Classifier: Topic :: System :: Systems Administration
Classifier: Topic :: System :: Monitoring
Classifier: Topic :: System :: Distributed Computing
Requires-Dist: click (>=6.7)
Requires-Dist: psycopg2 (>=2.6.2)
Requires-Dist: pyyaml (>=3.12)
Requires-Dist: redis (>=2.10.5)
